{
  "generator-jhipster": {
    "promptValues": {
      "packageName": "com",
      "nativeLanguage": "it"
    },
    "jhipsterVersion": "5.2.1",
    "applicationType": "gateway",
    "baseName": "gateway",
    "packageName": "com",
    "packageFolder": "com",
    "serverPort": "8080",
    "authenticationType": "jwt",
    "cacheProvider": "hazelcast",
    "enableHibernateCache": false,
    "websocket": "spring-websocket",
    "databaseType": "sql",
    "devDatabaseType": "h2Disk",
    "prodDatabaseType": "mysql",
    "searchEngine": false,
    "messageBroker": false,
    "serviceDiscoveryType": "consul",
    "buildTool": "maven",
    "enableSwaggerCodegen": false,
    "jwtSecretKey": "5ee5cb1c65625aee7480b7d09ec008a977f9e74e",
    "clientFramework": "angularX",
    "useSass": true,
    "clientPackageManager": "npm",
    "testFrameworks": [
      "protractor"
    ],
    "jhiPrefix": "jhi",
    "enableTranslation": true,
    "nativeLanguage": "it",
    "languages": [
      "it",
      "en"
    ]
  }
}